[
  {
    "name": "Overall",
    "headers": [
      "PLAYER_ID",
      "PLAYER_NAME_LAST_FIRST",
      "SORT_ORDER",
      "GP",
      "G",
      "SHOT_TYPE",
      "FGA_FREQUENCY",
      "FGM",
      "FGA",
      "FG_PCT",
      "EFG_PCT",
      "FG2A_FREQUENCY",
      "FG2M",
      "FG2A",
      "FG2_PCT",
      "FG3A_FREQUENCY",
      "FG3M",
      "FG3A",
      "FG3_PCT"
    ],
    "rowSet": [
      [
        203110,
        "Green, Draymond",
        1,
        37,
        37,
        "Overall",
        1,
        2.3,
        5.73,
        0.401,
        0.443,
        0.66,
        1.81,
        3.78,
        0.479,
        0.34,
        0.49,
        1.95,
        0.25
      ]
    ]
  },
  {
    "name": "GeneralShooting",
    "headers": [
      "PLAYER_ID",
      "PLAYER_NAME_LAST_FIRST",
      "SORT_ORDER",
      "GP",
      "G",
      "SHOT_TYPE",
      "FGA_FREQUENCY",
      "FGM",
      "FGA",
      "FG_PCT",
      "EFG_PCT",
      "FG2A_FREQUENCY",
      "FG2M",
      "FG2A",
      "FG2_PCT",
      "FG3A_FREQUENCY",
      "FG3M",
      "FG3A",
      "FG3_PCT"
    ],
    "rowSet": [
      [
        203110,
        "Green, Draymond",
        1,
        37,
        31,
        "Catch and Shoot",
        0.335,
        0.51,
        1.92,
        0.268,
        0.387,
        0.033,
        0.05,
        0.19,
        0.286,
        0.302,
        0.46,
        1.73,
        0.266
      ],
      [
        203110,
        "Green, Draymond",
        2,
        37,
        15,
        "Pull Ups",
        0.094,
        0.03,
        0.54,
        0.05,
        0.05,
        0.061,
        0.03,
        0.35,
        0.077,
        0.033,
        0,
        0.19,
        0
      ],
      [
        203110,
        "Green, Draymond",
        3,
        37,
        33,
        "Less than 10 ft",
        0.561,
        1.73,
        3.22,
        0.538,
        0.538,
        0.561,
        1.73,
        3.22,
        0.538,
        0,
        0,
        0,
        null
      ],
      [
        203110,
        "Green, Draymond",
        4,
        37,
        2,
        "Other",
        0.009,
        0.03,
        0.05,
        0.5,
        0.75,
        0.005,
        0,
        0.03,
        0,
        0.005,
        0.03,
        0.03,
        1
      ]
    ]
  },
  {
    "name": "ShotClockShooting",
    "headers": [
      "PLAYER_ID",
      "PLAYER_NAME_LAST_FIRST",
      "SORT_ORDER",
      "GP",
      "G",
      "SHOT_CLOCK_RANGE",
      "FGA_FREQUENCY",
      "FGM",
      "FGA",
      "FG_PCT",
      "EFG_PCT",
      "FG2A_FREQUENCY",
      "FG2M",
      "FG2A",
      "FG2_PCT",
      "FG3A_FREQUENCY",
      "FG3M",
      "FG3A",
      "FG3_PCT"
    ],
    "rowSet": [
      [
        203110,
        "Green, Draymond",
        1,
        37,
        5,
        "24-22",
        0.024,
        0.03,
        0.14,
        0.2,
        0.2,
        0.024,
        0.03,
        0.14,
        0.2,
        0,
        0,
        0,
        null
      ],
      [
        203110,
        "Green, Draymond",
        2,
        37,
        19,
        "22-18 Very Early",
        0.17,
        0.49,
        0.97,
        0.5,
        0.5,
        0.156,
        0.49,
        0.89,
        0.545,
        0.014,
        0,
        0.08,
        0
      ],
      [
        203110,
        "Green, Draymond",
        3,
        37,
        29,
        "18-15 Early",
        0.222,
        0.59,
        1.27,
        0.468,
        0.532,
        0.151,
        0.43,
        0.86,
        0.5,
        0.071,
        0.16,
        0.41,
        0.4
      ],
      [
        203110,
        "Green, Draymond",
        4,
        37,
        35,
        "15-7 Average",
        0.41,
        0.78,
        2.35,
        0.333,
        0.368,
        0.264,
        0.62,
        1.51,
        0.411,
        0.146,
        0.16,
        0.84,
        0.194
      ],
      [
        203110,
        "Green, Draymond",
        5,
        37,
        14,
        "7-4 Late",
        0.075,
        0.16,
        0.43,
        0.375,
        0.438,
        0.038,
        0.11,
        0.22,
        0.5,
        0.038,
        0.05,
        0.22,
        0.25
      ],
      [
        203110,
        "Green, Draymond",
        6,
        37,
        17,
        "4-0 Very Late",
        0.099,
        0.24,
        0.57,
        0.429,
        0.524,
        0.028,
        0.14,
        0.16,
        0.833,
        0.071,
        0.11,
        0.41,
        0.267
      ]
    ]
  },
  {
    "name": "DribbleShooting",
    "headers": [
      "PLAYER_ID",
      "PLAYER_NAME_LAST_FIRST",
      "SORT_ORDER",
      "GP",
      "G",
      "DRIBBLE_RANGE",
      "FGA_FREQUENCY",
      "FGM",
      "FGA",
      "FG_PCT",
      "EFG_PCT",
      "FG2A_FREQUENCY",
      "FG2M",
      "FG2A",
      "FG2_PCT",
      "FG3A_FREQUENCY",
      "FG3M",
      "FG3A",
      "FG3_PCT"
    ],
    "rowSet": [
      [
        203110,
        "Green, Draymond",
        1,
        37,
        36,
        "0 Dribbles",
        0.519,
        1.14,
        2.97,
        0.382,
        0.464,
        0.212,
        0.65,
        1.22,
        0.533,
        0.307,
        0.49,
        1.76,
        0.277
      ],
      [
        203110,
        "Green, Draymond",
        2,
        37,
        27,
        "1 Dribble",
        0.236,
        0.62,
        1.35,
        0.46,
        0.46,
        0.208,
        0.62,
        1.19,
        0.523,
        0.028,
        0,
        0.16,
        0
      ],
      [
        203110,
        "Green, Draymond",
        3,
        37,
        14,
        "2 Dribbles",
        0.08,
        0.11,
        0.46,
        0.235,
        0.235,
        0.075,
        0.11,
        0.43,
        0.25,
        0.005,
        0,
        0.03,
        0
      ],
      [
        203110,
        "Green, Draymond",
        4,
        37,
        16,
        "3-6 Dribbles",
        0.094,
        0.22,
        0.54,
        0.4,
        0.4,
        0.094,
        0.22,
        0.54,
        0.4,
        0,
        0,
        0,
        null
      ],
      [
        203110,
        "Green, Draymond",
        5,
        37,
        14,
        "7+ Dribbles",
        0.071,
        0.22,
        0.41,
        0.533,
        0.533,
        0.071,
        0.22,
        0.41,
        0.533,
        0,
        0,
        0,
        null
      ]
    ]
  },
  {
    "name": "ClosestDefenderShooting",
    "headers": [
      "PLAYER_ID",
      "PLAYER_NAME_LAST_FIRST",
      "SORT_ORDER",
      "GP",
      "G",
      "CLOSE_DEF_DIST_RANGE",
      "FGA_FREQUENCY",
      "FGM",
      "FGA",
      "FG_PCT",
      "EFG_PCT",
      "FG2A_FREQUENCY",
      "FG2M",
      "FG2A",
      "FG2_PCT",
      "FG3A_FREQUENCY",
      "FG3M",
      "FG3A",
      "FG3_PCT"
    ],
    "rowSet": [
      [
        203110,
        "Green, Draymond",
        1,
        37,
        16,
        "0-2 Feet - Very Tight",
        0.094,
        0.24,
        0.54,
        0.45,
        0.45,
        0.09,
        0.24,
        0.51,
        0.474,
        0.005,
        0,
        0.03,
        0
      ],
      [
        203110,
        "Green, Draymond",
        2,
        37,
        34,
        "2-4 Feet - Tight",
        0.396,
        1.11,
        2.27,
        0.488,
        0.488,
        0.392,
        1.11,
        2.24,
        0.494,
        0.005,
        0,
        0.03,
        0
      ],
      [
        203110,
        "Green, Draymond",
        3,
        37,
        24,
        "4-6 Feet - Open",
        0.198,
        0.38,
        1.14,
        0.333,
        0.369,
        0.132,
        0.3,
        0.76,
        0.393,
        0.066,
        0.08,
        0.38,
        0.214
      ],
      [
        203110,
        "Green, Draymond",
        4,
        37,
        31,
        "6+ Feet - Wide Open",
        0.311,
        0.57,
        1.78,
        0.318,
        0.432,
        0.047,
        0.16,
        0.27,
        0.6,
        0.264,
        0.41,
        1.51,
        0.268
      ]
    ]
  },
  {
    "name": "ClosestDefender10ftPlusShooting",
    "headers": [
      "PLAYER_ID",
      "PLAYER_NAME_LAST_FIRST",
      "SORT_ORDER",
      "GP",
      "G",
      "CLOSE_DEF_DIST_RANGE",
      "FGA_FREQUENCY",
      "FGM",
      "FGA",
      "FG_PCT",
      "EFG_PCT",
      "FG2A_FREQUENCY",
      "FG2M",
      "FG2A",
      "FG2_PCT",
      "FG3A_FREQUENCY",
      "FG3M",
      "FG3A",
      "FG3_PCT"
    ],
    "rowSet": [
      [
        203110,
        "Green, Draymond",
        1,
        37,
        2,
        "0-2 Feet - Very Tight",
        0.009,
        0,
        0.05,
        0,
        0,
        0.005,
        0,
        0.03,
        0,
        0.005,
        0,
        0.03,
        0
      ],
      [
        203110,
        "Green, Draymond",
        2,
        37,
        5,
        "2-4 Feet - Tight",
        0.028,
        0.05,
        0.16,
        0.333,
        0.333,
        0.024,
        0.05,
        0.14,
        0.4,
        0.005,
        0,
        0.03,
        0
      ],
      [
        203110,
        "Green, Draymond",
        3,
        37,
        18,
        "4-6 Feet - Open",
        0.113,
        0.08,
        0.65,
        0.125,
        0.188,
        0.047,
        0,
        0.27,
        0,
        0.066,
        0.08,
        0.38,
        0.214
      ],
      [
        203110,
        "Green, Draymond",
        4,
        37,
        30,
        "6+ Feet - Wide Open",
        0.288,
        0.43,
        1.65,
        0.262,
        0.385,
        0.024,
        0.03,
        0.14,
        0.2,
        0.264,
        0.41,
        1.51,
        0.268
      ]
    ]
  },
  {
    "name": "TouchTimeShooting",
    "headers": [
      "PLAYER_ID",
      "PLAYER_NAME_LAST_FIRST",
      "SORT_ORDER",
      "GP",
      "G",
      "TOUCH_TIME_RANGE",
      "FGA_FREQUENCY",
      "FGM",
      "FGA",
      "FG_PCT",
      "EFG_PCT",
      "FG2A_FREQUENCY",
      "FG2M",
      "FG2A",
      "FG2_PCT",
      "FG3A_FREQUENCY",
      "FG3M",
      "FG3A",
      "FG3_PCT"
    ],
    "rowSet": [
      [
        203110,
        "Green, Draymond",
        1,
        37,
        37,
        "Touch < 2 Seconds",
        0.679,
        1.51,
        3.89,
        0.389,
        0.448,
        0.358,
        1.05,
        2.05,
        0.513,
        0.321,
        0.46,
        1.84,
        0.25
      ],
      [
        203110,
        "Green, Draymond",
        2,
        37,
        31,
        "Touch 2-6 Seconds",
        0.259,
        0.62,
        1.49,
        0.418,
        0.427,
        0.245,
        0.59,
        1.41,
        0.423,
        0.014,
        0.03,
        0.08,
        0.333
      ],
      [
        203110,
        "Green, Draymond",
        3,
        37,
        13,
        "Touch 6+ Seconds",
        0.061,
        0.16,
        0.35,
        0.462,
        0.462,
        0.057,
        0.16,
        0.32,
        0.5,
        0.005,
        0,
        0.03,
        0
      ]
    ]
  }
]