[
  {
    "name": "Overall",
    "headers": [
      "PLAYER_ID",
      "PLAYER_NAME_LAST_FIRST",
      "SORT_ORDER",
      "GP",
      "G",
      "SHOT_TYPE",
      "FGA_FREQUENCY",
      "FGM",
      "FGA",
      "FG_PCT",
      "EFG_PCT",
      "FG2A_FREQUENCY",
      "FG2M",
      "FG2A",
      "FG2_PCT",
      "FG3A_FREQUENCY",
      "FG3M",
      "FG3A",
      "FG3_PCT"
    ],
    "rowSet": [
      [
        200746,
        "Aldridge, LaMarcus",
        1,
        75,
        75,
        "Overall",
        1,
        9.16,
        17.37,
        0.527,
        0.538,
        0.93,
        8.8,
        16.16,
        0.545,
        0.07,
        0.36,
        1.21,
        0.297
      ]
    ]
  },
  {
    "name": "GeneralShooting",
    "headers": [
      "PLAYER_ID",
      "PLAYER_NAME_LAST_FIRST",
      "SORT_ORDER",
      "GP",
      "G",
      "SHOT_TYPE",
      "FGA_FREQUENCY",
      "FGM",
      "FGA",
      "FG_PCT",
      "EFG_PCT",
      "FG2A_FREQUENCY",
      "FG2M",
      "FG2A",
      "FG2_PCT",
      "FG3A_FREQUENCY",
      "FG3M",
      "FG3A",
      "FG3_PCT"
    ],
    "rowSet": [
      [
        200746,
        "Aldridge, LaMarcus",
        1,
        75,
        71,
        "Catch and Shoot",
        0.211,
        1.55,
        3.67,
        0.422,
        0.465,
        0.149,
        1.23,
        2.59,
        0.474,
        0.062,
        0.32,
        1.08,
        0.296
      ],
      [
        200746,
        "Aldridge, LaMarcus",
        2,
        75,
        75,
        "Pull Ups",
        0.312,
        2.27,
        5.43,
        0.418,
        0.421,
        0.305,
        2.23,
        5.29,
        0.421,
        0.008,
        0.04,
        0.13,
        0.3
      ],
      [
        200746,
        "Aldridge, LaMarcus",
        3,
        75,
        75,
        "Less than 10 ft",
        0.46,
        5.24,
        8,
        0.655,
        0.655,
        0.46,
        5.24,
        8,
        0.655,
        0,
        0,
        0,
        null
      ],
      [
        200746,
        "Aldridge, LaMarcus",
        4,
        75,
        20,
        "Other",
        0.016,
        0.11,
        0.28,
        0.381,
        0.381,
        0.016,
        0.11,
        0.28,
        0.381,
        0,
        0,
        0,
        null
      ]
    ]
  },
  {
    "name": "ShotClockShooting",
    "headers": [
      "PLAYER_ID",
      "PLAYER_NAME_LAST_FIRST",
      "SORT_ORDER",
      "GP",
      "G",
      "SHOT_CLOCK_RANGE",
      "FGA_FREQUENCY",
      "FGM",
      "FGA",
      "FG_PCT",
      "EFG_PCT",
      "FG2A_FREQUENCY",
      "FG2M",
      "FG2A",
      "FG2_PCT",
      "FG3A_FREQUENCY",
      "FG3M",
      "FG3A",
      "FG3_PCT"
    ],
    "rowSet": [
      [
        200746,
        "Aldridge, LaMarcus",
        1,
        75,
        56,
        "24-22",
        0.076,
        1,
        1.32,
        0.758,
        0.758,
        0.076,
        1,
        1.32,
        0.758,
        0,
        0,
        0,
        null
      ],
      [
        200746,
        "Aldridge, LaMarcus",
        2,
        75,
        32,
        "22-18 Very Early",
        0.035,
        0.44,
        0.6,
        0.733,
        0.767,
        0.032,
        0.4,
        0.56,
        0.714,
        0.002,
        0.04,
        0.04,
        1
      ],
      [
        200746,
        "Aldridge, LaMarcus",
        3,
        75,
        60,
        "18-15 Early",
        0.104,
        0.99,
        1.81,
        0.544,
        0.563,
        0.092,
        0.92,
        1.6,
        0.575,
        0.012,
        0.07,
        0.21,
        0.313
      ],
      [
        200746,
        "Aldridge, LaMarcus",
        4,
        75,
        75,
        "15-7 Average",
        0.543,
        4.96,
        9.43,
        0.526,
        0.532,
        0.522,
        4.85,
        9.07,
        0.535,
        0.021,
        0.11,
        0.36,
        0.296
      ],
      [
        200746,
        "Aldridge, LaMarcus",
        5,
        75,
        69,
        "7-4 Late",
        0.154,
        1.32,
        2.68,
        0.493,
        0.512,
        0.144,
        1.21,
        2.49,
        0.487,
        0.011,
        0.11,
        0.19,
        0.571
      ],
      [
        200746,
        "Aldridge, LaMarcus",
        6,
        75,
        59,
        "4-0 Very Late",
        0.088,
        0.45,
        1.53,
        0.296,
        0.309,
        0.064,
        0.41,
        1.12,
        0.369,
        0.024,
        0.04,
        0.41,
        0.097
      ]
    ]
  },
  {
    "name": "DribbleShooting",
    "headers": [
      "PLAYER_ID",
      "PLAYER_NAME_LAST_FIRST",
      "SORT_ORDER",
      "GP",
      "G",
      "DRIBBLE_RANGE",
      "FGA_FREQUENCY",
      "FGM",
      "FGA",
      "FG_PCT",
      "EFG_PCT",
      "FG2A_FREQUENCY",
      "FG2M",
      "FG2A",
      "FG2_PCT",
      "FG3A_FREQUENCY",
      "FG3M",
      "FG3A",
      "FG3_PCT"
    ],
    "rowSet": [
      [
        200746,
        "Aldridge, LaMarcus",
        1,
        75,
        75,
        "0 Dribbles",
        0.444,
        4.55,
        7.71,
        0.59,
        0.611,
        0.381,
        4.23,
        6.63,
        0.638,
        0.062,
        0.32,
        1.08,
        0.296
      ],
      [
        200746,
        "Aldridge, LaMarcus",
        2,
        75,
        67,
        "1 Dribble",
        0.157,
        1.47,
        2.72,
        0.539,
        0.544,
        0.15,
        1.44,
        2.61,
        0.551,
        0.006,
        0.03,
        0.11,
        0.25
      ],
      [
        200746,
        "Aldridge, LaMarcus",
        3,
        75,
        70,
        "2 Dribbles",
        0.144,
        1.13,
        2.51,
        0.452,
        0.452,
        0.144,
        1.13,
        2.49,
        0.455,
        0.001,
        0,
        0.01,
        0
      ],
      [
        200746,
        "Aldridge, LaMarcus",
        4,
        75,
        72,
        "3-6 Dribbles",
        0.249,
        1.92,
        4.33,
        0.443,
        0.445,
        0.249,
        1.91,
        4.32,
        0.441,
        0.001,
        0.01,
        0.01,
        1
      ],
      [
        200746,
        "Aldridge, LaMarcus",
        5,
        75,
        8,
        "7+ Dribbles",
        0.006,
        0.09,
        0.11,
        0.875,
        0.875,
        0.006,
        0.09,
        0.11,
        0.875,
        0,
        0,
        0,
        null
      ]
    ]
  },
  {
    "name": "ClosestDefenderShooting",
    "headers": [
      "PLAYER_ID",
      "PLAYER_NAME_LAST_FIRST",
      "SORT_ORDER",
      "GP",
      "G",
      "CLOSE_DEF_DIST_RANGE",
      "FGA_FREQUENCY",
      "FGM",
      "FGA",
      "FG_PCT",
      "EFG_PCT",
      "FG2A_FREQUENCY",
      "FG2M",
      "FG2A",
      "FG2_PCT",
      "FG3A_FREQUENCY",
      "FG3M",
      "FG3A",
      "FG3_PCT"
    ],
    "rowSet": [
      [
        200746,
        "Aldridge, LaMarcus",
        1,
        75,
        62,
        "0-2 Feet - Very Tight",
        0.125,
        1.2,
        2.17,
        0.552,
        0.552,
        0.124,
        1.2,
        2.16,
        0.556,
        0.001,
        0,
        0.01,
        0
      ],
      [
        200746,
        "Aldridge, LaMarcus",
        2,
        75,
        75,
        "2-4 Feet - Tight",
        0.503,
        4.88,
        8.73,
        0.559,
        0.56,
        0.496,
        4.87,
        8.61,
        0.565,
        0.007,
        0.01,
        0.12,
        0.111
      ],
      [
        200746,
        "Aldridge, LaMarcus",
        3,
        75,
        74,
        "4-6 Feet - Open",
        0.224,
        1.96,
        3.89,
        0.503,
        0.514,
        0.212,
        1.88,
        3.68,
        0.511,
        0.012,
        0.08,
        0.21,
        0.375
      ],
      [
        200746,
        "Aldridge, LaMarcus",
        4,
        75,
        65,
        "6+ Feet - Wide Open",
        0.148,
        1.12,
        2.57,
        0.435,
        0.487,
        0.098,
        0.85,
        1.71,
        0.5,
        0.05,
        0.27,
        0.87,
        0.308
      ]
    ]
  },
  {
    "name": "ClosestDefender10ftPlusShooting",
    "headers": [
      "PLAYER_ID",
      "PLAYER_NAME_LAST_FIRST",
      "SORT_ORDER",
      "GP",
      "G",
      "CLOSE_DEF_DIST_RANGE",
      "FGA_FREQUENCY",
      "FGM",
      "FGA",
      "FG_PCT",
      "EFG_PCT",
      "FG2A_FREQUENCY",
      "FG2M",
      "FG2A",
      "FG2_PCT",
      "FG3A_FREQUENCY",
      "FG3M",
      "FG3A",
      "FG3_PCT"
    ],
    "rowSet": [
      [
        200746,
        "Aldridge, LaMarcus",
        1,
        75,
        14,
        "0-2 Feet - Very Tight",
        0.011,
        0.04,
        0.19,
        0.214,
        0.214,
        0.01,
        0.04,
        0.17,
        0.231,
        0.001,
        0,
        0.01,
        0
      ],
      [
        200746,
        "Aldridge, LaMarcus",
        2,
        75,
        74,
        "2-4 Feet - Tight",
        0.206,
        1.49,
        3.59,
        0.416,
        0.418,
        0.2,
        1.48,
        3.47,
        0.427,
        0.007,
        0.01,
        0.12,
        0.111
      ],
      [
        200746,
        "Aldridge, LaMarcus",
        3,
        75,
        72,
        "4-6 Feet - Open",
        0.182,
        1.4,
        3.16,
        0.443,
        0.456,
        0.17,
        1.32,
        2.95,
        0.448,
        0.012,
        0.08,
        0.21,
        0.375
      ],
      [
        200746,
        "Aldridge, LaMarcus",
        4,
        75,
        64,
        "6+ Feet - Wide Open",
        0.14,
        0.99,
        2.44,
        0.404,
        0.459,
        0.091,
        0.72,
        1.57,
        0.458,
        0.05,
        0.27,
        0.87,
        0.308
      ]
    ]
  },
  {
    "name": "TouchTimeShooting",
    "headers": [
      "PLAYER_ID",
      "PLAYER_NAME_LAST_FIRST",
      "SORT_ORDER",
      "GP",
      "G",
      "TOUCH_TIME_RANGE",
      "FGA_FREQUENCY",
      "FGM",
      "FGA",
      "FG_PCT",
      "EFG_PCT",
      "FG2A_FREQUENCY",
      "FG2M",
      "FG2A",
      "FG2_PCT",
      "FG3A_FREQUENCY",
      "FG3M",
      "FG3A",
      "FG3_PCT"
    ],
    "rowSet": [
      [
        200746,
        "Aldridge, LaMarcus",
        1,
        75,
        75,
        "Touch < 2 Seconds",
        0.495,
        5.07,
        8.6,
        0.589,
        0.608,
        0.429,
        4.75,
        7.45,
        0.637,
        0.066,
        0.32,
        1.15,
        0.279
      ],
      [
        200746,
        "Aldridge, LaMarcus",
        2,
        75,
        75,
        "Touch 2-6 Seconds",
        0.448,
        3.69,
        7.79,
        0.474,
        0.477,
        0.444,
        3.65,
        7.72,
        0.473,
        0.004,
        0.04,
        0.07,
        0.6
      ],
      [
        200746,
        "Aldridge, LaMarcus",
        3,
        75,
        43,
        "Touch 6+ Seconds",
        0.057,
        0.4,
        0.99,
        0.405,
        0.405,
        0.057,
        0.4,
        0.99,
        0.405,
        0,
        0,
        0,
        null
      ]
    ]
  }
]