[
  {
    "name": "Overall",
    "headers": [
      "PLAYER_ID",
      "PLAYER_NAME_LAST_FIRST",
      "SORT_ORDER",
      "GP",
      "G",
      "SHOT_TYPE",
      "FGA_FREQUENCY",
      "FGM",
      "FGA",
      "FG_PCT",
      "EFG_PCT",
      "FG2A_FREQUENCY",
      "FG2M",
      "FG2A",
      "FG2_PCT",
      "FG3A_FREQUENCY",
      "FG3M",
      "FG3A",
      "FG3_PCT"
    ],
    "rowSet": [
      [
        1626181,
        "Powell, Norman",
        1,
        60,
        59,
        "Overall",
        1,
        3.22,
        6.67,
        0.483,
        0.568,
        0.575,
        2.08,
        3.83,
        0.543,
        0.425,
        1.13,
        2.83,
        0.4
      ]
    ]
  },
  {
    "name": "GeneralShooting",
    "headers": [
      "PLAYER_ID",
      "PLAYER_NAME_LAST_FIRST",
      "SORT_ORDER",
      "GP",
      "G",
      "SHOT_TYPE",
      "FGA_FREQUENCY",
      "FGM",
      "FGA",
      "FG_PCT",
      "EFG_PCT",
      "FG2A_FREQUENCY",
      "FG2M",
      "FG2A",
      "FG2_PCT",
      "FG3A_FREQUENCY",
      "FG3M",
      "FG3A",
      "FG3_PCT"
    ],
    "rowSet": [
      [
        1626181,
        "Powell, Norman",
        1,
        60,
        54,
        "Catch and Shoot",
        0.345,
        1,
        2.3,
        0.435,
        0.638,
        0.02,
        0.07,
        0.13,
        0.5,
        0.325,
        0.93,
        2.17,
        0.431
      ],
      [
        1626181,
        "Powell, Norman",
        2,
        60,
        40,
        "Pull Ups",
        0.195,
        0.37,
        1.3,
        0.282,
        0.359,
        0.098,
        0.17,
        0.65,
        0.256,
        0.098,
        0.2,
        0.65,
        0.308
      ],
      [
        1626181,
        "Powell, Norman",
        3,
        60,
        54,
        "Less than 10 ft",
        0.458,
        1.85,
        3.05,
        0.607,
        0.607,
        0.458,
        1.85,
        3.05,
        0.607,
        0,
        0,
        0,
        null
      ],
      [
        1626181,
        "Powell, Norman",
        4,
        60,
        1,
        "Other",
        0.003,
        0,
        0.02,
        0,
        0,
        0,
        0,
        0,
        null,
        0.003,
        0,
        0.02,
        0
      ]
    ]
  },
  {
    "name": "ShotClockShooting",
    "headers": [
      "PLAYER_ID",
      "PLAYER_NAME_LAST_FIRST",
      "SORT_ORDER",
      "GP",
      "G",
      "SHOT_CLOCK_RANGE",
      "FGA_FREQUENCY",
      "FGM",
      "FGA",
      "FG_PCT",
      "EFG_PCT",
      "FG2A_FREQUENCY",
      "FG2M",
      "FG2A",
      "FG2_PCT",
      "FG3A_FREQUENCY",
      "FG3M",
      "FG3A",
      "FG3_PCT"
    ],
    "rowSet": [
      [
        1626181,
        "Powell, Norman",
        1,
        60,
        7,
        "24-22",
        0.018,
        0.1,
        0.12,
        0.857,
        0.857,
        0.018,
        0.1,
        0.12,
        0.857,
        0,
        0,
        0,
        null
      ],
      [
        1626181,
        "Powell, Norman",
        2,
        60,
        42,
        "22-18 Very Early",
        0.205,
        0.73,
        1.37,
        0.537,
        0.591,
        0.13,
        0.58,
        0.87,
        0.673,
        0.075,
        0.15,
        0.5,
        0.3
      ],
      [
        1626181,
        "Powell, Norman",
        3,
        60,
        35,
        "18-15 Early",
        0.128,
        0.45,
        0.85,
        0.529,
        0.618,
        0.08,
        0.3,
        0.53,
        0.563,
        0.048,
        0.15,
        0.32,
        0.474
      ],
      [
        1626181,
        "Powell, Norman",
        4,
        60,
        54,
        "15-7 Average",
        0.413,
        1.3,
        2.75,
        0.473,
        0.555,
        0.248,
        0.85,
        1.65,
        0.515,
        0.165,
        0.45,
        1.1,
        0.409
      ],
      [
        1626181,
        "Powell, Norman",
        5,
        60,
        28,
        "7-4 Late",
        0.105,
        0.32,
        0.7,
        0.452,
        0.583,
        0.055,
        0.13,
        0.37,
        0.364,
        0.05,
        0.18,
        0.33,
        0.55
      ],
      [
        1626181,
        "Powell, Norman",
        6,
        60,
        34,
        "4-0 Very Late",
        0.133,
        0.32,
        0.88,
        0.358,
        0.472,
        0.045,
        0.12,
        0.3,
        0.389,
        0.088,
        0.2,
        0.58,
        0.343
      ]
    ]
  },
  {
    "name": "DribbleShooting",
    "headers": [
      "PLAYER_ID",
      "PLAYER_NAME_LAST_FIRST",
      "SORT_ORDER",
      "GP",
      "G",
      "DRIBBLE_RANGE",
      "FGA_FREQUENCY",
      "FGM",
      "FGA",
      "FG_PCT",
      "EFG_PCT",
      "FG2A_FREQUENCY",
      "FG2M",
      "FG2A",
      "FG2_PCT",
      "FG3A_FREQUENCY",
      "FG3M",
      "FG3A",
      "FG3_PCT"
    ],
    "rowSet": [
      [
        1626181,
        "Powell, Norman",
        1,
        60,
        56,
        "0 Dribbles",
        0.418,
        1.33,
        2.78,
        0.479,
        0.647,
        0.09,
        0.4,
        0.6,
        0.667,
        0.328,
        0.93,
        2.18,
        0.427
      ],
      [
        1626181,
        "Powell, Norman",
        2,
        60,
        25,
        "1 Dribble",
        0.073,
        0.32,
        0.48,
        0.655,
        0.707,
        0.058,
        0.27,
        0.38,
        0.696,
        0.015,
        0.05,
        0.1,
        0.5
      ],
      [
        1626181,
        "Powell, Norman",
        3,
        60,
        40,
        "2 Dribbles",
        0.15,
        0.57,
        1,
        0.567,
        0.6,
        0.12,
        0.5,
        0.8,
        0.625,
        0.03,
        0.07,
        0.2,
        0.333
      ],
      [
        1626181,
        "Powell, Norman",
        4,
        60,
        47,
        "3-6 Dribbles",
        0.285,
        0.8,
        1.9,
        0.421,
        0.443,
        0.24,
        0.72,
        1.6,
        0.448,
        0.045,
        0.08,
        0.3,
        0.278
      ],
      [
        1626181,
        "Powell, Norman",
        5,
        60,
        26,
        "7+ Dribbles",
        0.075,
        0.2,
        0.5,
        0.4,
        0.4,
        0.068,
        0.2,
        0.45,
        0.444,
        0.008,
        0,
        0.05,
        0
      ]
    ]
  },
  {
    "name": "ClosestDefenderShooting",
    "headers": [
      "PLAYER_ID",
      "PLAYER_NAME_LAST_FIRST",
      "SORT_ORDER",
      "GP",
      "G",
      "CLOSE_DEF_DIST_RANGE",
      "FGA_FREQUENCY",
      "FGM",
      "FGA",
      "FG_PCT",
      "EFG_PCT",
      "FG2A_FREQUENCY",
      "FG2M",
      "FG2A",
      "FG2_PCT",
      "FG3A_FREQUENCY",
      "FG3M",
      "FG3A",
      "FG3_PCT"
    ],
    "rowSet": [
      [
        1626181,
        "Powell, Norman",
        1,
        60,
        38,
        "0-2 Feet - Very Tight",
        0.13,
        0.32,
        0.87,
        0.365,
        0.375,
        0.128,
        0.3,
        0.85,
        0.353,
        0.003,
        0.02,
        0.02,
        1
      ],
      [
        1626181,
        "Powell, Norman",
        2,
        60,
        54,
        "2-4 Feet - Tight",
        0.35,
        1.33,
        2.33,
        0.571,
        0.586,
        0.31,
        1.27,
        2.07,
        0.613,
        0.04,
        0.07,
        0.27,
        0.25
      ],
      [
        1626181,
        "Powell, Norman",
        3,
        60,
        46,
        "4-6 Feet - Open",
        0.278,
        0.75,
        1.85,
        0.405,
        0.527,
        0.1,
        0.3,
        0.67,
        0.45,
        0.178,
        0.45,
        1.18,
        0.38
      ],
      [
        1626181,
        "Powell, Norman",
        4,
        60,
        46,
        "6+ Feet - Wide Open",
        0.243,
        0.82,
        1.62,
        0.505,
        0.691,
        0.038,
        0.22,
        0.25,
        0.867,
        0.205,
        0.6,
        1.37,
        0.439
      ]
    ]
  },
  {
    "name": "ClosestDefender10ftPlusShooting",
    "headers": [
      "PLAYER_ID",
      "PLAYER_NAME_LAST_FIRST",
      "SORT_ORDER",
      "GP",
      "G",
      "CLOSE_DEF_DIST_RANGE",
      "FGA_FREQUENCY",
      "FGM",
      "FGA",
      "FG_PCT",
      "EFG_PCT",
      "FG2A_FREQUENCY",
      "FG2M",
      "FG2A",
      "FG2_PCT",
      "FG3A_FREQUENCY",
      "FG3M",
      "FG3A",
      "FG3_PCT"
    ],
    "rowSet": [
      [
        1626181,
        "Powell, Norman",
        1,
        60,
        4,
        "0-2 Feet - Very Tight",
        0.01,
        0.02,
        0.07,
        0.25,
        0.375,
        0.008,
        0,
        0.05,
        0,
        0.003,
        0.02,
        0.02,
        1
      ],
      [
        1626181,
        "Powell, Norman",
        2,
        60,
        24,
        "2-4 Feet - Tight",
        0.08,
        0.18,
        0.53,
        0.344,
        0.406,
        0.04,
        0.12,
        0.27,
        0.438,
        0.04,
        0.07,
        0.27,
        0.25
      ],
      [
        1626181,
        "Powell, Norman",
        3,
        60,
        43,
        "4-6 Feet - Open",
        0.233,
        0.5,
        1.55,
        0.323,
        0.468,
        0.055,
        0.05,
        0.37,
        0.136,
        0.178,
        0.45,
        1.18,
        0.38
      ],
      [
        1626181,
        "Powell, Norman",
        4,
        60,
        44,
        "6+ Feet - Wide Open",
        0.22,
        0.67,
        1.47,
        0.455,
        0.659,
        0.015,
        0.07,
        0.1,
        0.667,
        0.205,
        0.6,
        1.37,
        0.439
      ]
    ]
  },
  {
    "name": "TouchTimeShooting",
    "headers": [
      "PLAYER_ID",
      "PLAYER_NAME_LAST_FIRST",
      "SORT_ORDER",
      "GP",
      "G",
      "TOUCH_TIME_RANGE",
      "FGA_FREQUENCY",
      "FGM",
      "FGA",
      "FG_PCT",
      "EFG_PCT",
      "FG2A_FREQUENCY",
      "FG2M",
      "FG2A",
      "FG2_PCT",
      "FG3A_FREQUENCY",
      "FG3M",
      "FG3A",
      "FG3_PCT"
    ],
    "rowSet": [
      [
        1626181,
        "Powell, Norman",
        1,
        60,
        58,
        "Touch < 2 Seconds",
        0.493,
        1.67,
        3.28,
        0.508,
        0.65,
        0.16,
        0.73,
        1.07,
        0.688,
        0.333,
        0.93,
        2.22,
        0.421
      ],
      [
        1626181,
        "Powell, Norman",
        2,
        60,
        53,
        "Touch 2-6 Seconds",
        0.423,
        1.33,
        2.82,
        0.473,
        0.509,
        0.34,
        1.13,
        2.27,
        0.5,
        0.083,
        0.2,
        0.55,
        0.364
      ],
      [
        1626181,
        "Powell, Norman",
        3,
        60,
        25,
        "Touch 6+ Seconds",
        0.085,
        0.22,
        0.57,
        0.382,
        0.382,
        0.075,
        0.22,
        0.5,
        0.433,
        0.01,
        0,
        0.07,
        0
      ]
    ]
  }
]