[
  {
    "name": "Overall",
    "headers": [
      "PLAYER_ID",
      "PLAYER_NAME_LAST_FIRST",
      "SORT_ORDER",
      "GP",
      "G",
      "SHOT_TYPE",
      "FGA_FREQUENCY",
      "FGM",
      "FGA",
      "FG_PCT",
      "EFG_PCT",
      "FG2A_FREQUENCY",
      "FG2M",
      "FG2A",
      "FG2_PCT",
      "FG3A_FREQUENCY",
      "FG3M",
      "FG3A",
      "FG3_PCT"
    ],
    "rowSet": [
      [
        1626195,
        "Hernangomez, Willy",
        1,
        58,
        57,
        "Overall",
        1,
        2.64,
        5.1,
        0.517,
        0.542,
        0.868,
        2.38,
        4.43,
        0.537,
        0.132,
        0.26,
        0.67,
        0.385
      ]
    ]
  },
  {
    "name": "GeneralShooting",
    "headers": [
      "PLAYER_ID",
      "PLAYER_NAME_LAST_FIRST",
      "SORT_ORDER",
      "GP",
      "G",
      "SHOT_TYPE",
      "FGA_FREQUENCY",
      "FGM",
      "FGA",
      "FG_PCT",
      "EFG_PCT",
      "FG2A_FREQUENCY",
      "FG2M",
      "FG2A",
      "FG2_PCT",
      "FG3A_FREQUENCY",
      "FG3M",
      "FG3A",
      "FG3_PCT"
    ],
    "rowSet": [
      [
        1626195,
        "Hernangomez, Willy",
        1,
        58,
        37,
        "Catch and Shoot",
        0.169,
        0.31,
        0.86,
        0.36,
        0.5,
        0.044,
        0.07,
        0.22,
        0.308,
        0.125,
        0.24,
        0.64,
        0.378
      ],
      [
        1626195,
        "Hernangomez, Willy",
        2,
        58,
        7,
        "Pull Ups",
        0.024,
        0.05,
        0.12,
        0.429,
        0.5,
        0.02,
        0.03,
        0.1,
        0.333,
        0.003,
        0.02,
        0.02,
        1
      ],
      [
        1626195,
        "Hernangomez, Willy",
        3,
        58,
        55,
        "Less than 10 ft",
        0.804,
        2.28,
        4.1,
        0.555,
        0.555,
        0.804,
        2.28,
        4.1,
        0.555,
        0,
        0,
        0,
        null
      ],
      [
        1626195,
        "Hernangomez, Willy",
        4,
        58,
        1,
        "Other",
        0.003,
        0,
        0.02,
        0,
        0,
        0,
        0,
        0,
        null,
        0.003,
        0,
        0.02,
        0
      ]
    ]
  },
  {
    "name": "ShotClockShooting",
    "headers": [
      "PLAYER_ID",
      "PLAYER_NAME_LAST_FIRST",
      "SORT_ORDER",
      "GP",
      "G",
      "SHOT_CLOCK_RANGE",
      "FGA_FREQUENCY",
      "FGM",
      "FGA",
      "FG_PCT",
      "EFG_PCT",
      "FG2A_FREQUENCY",
      "FG2M",
      "FG2A",
      "FG2_PCT",
      "FG3A_FREQUENCY",
      "FG3M",
      "FG3A",
      "FG3_PCT"
    ],
    "rowSet": [
      [
        1626195,
        "Hernangomez, Willy",
        1,
        58,
        24,
        "24-22",
        0.118,
        0.31,
        0.6,
        0.514,
        0.514,
        0.118,
        0.31,
        0.6,
        0.514,
        0,
        0,
        0,
        null
      ],
      [
        1626195,
        "Hernangomez, Willy",
        2,
        58,
        10,
        "22-18 Very Early",
        0.047,
        0.17,
        0.24,
        0.714,
        0.75,
        0.041,
        0.16,
        0.21,
        0.75,
        0.007,
        0.02,
        0.03,
        0.5
      ],
      [
        1626195,
        "Hernangomez, Willy",
        3,
        58,
        34,
        "18-15 Early",
        0.149,
        0.36,
        0.76,
        0.477,
        0.511,
        0.118,
        0.31,
        0.6,
        0.514,
        0.03,
        0.05,
        0.16,
        0.333
      ],
      [
        1626195,
        "Hernangomez, Willy",
        4,
        58,
        52,
        "15-7 Average",
        0.503,
        1.29,
        2.57,
        0.503,
        0.52,
        0.453,
        1.21,
        2.31,
        0.522,
        0.051,
        0.09,
        0.26,
        0.333
      ],
      [
        1626195,
        "Hernangomez, Willy",
        5,
        58,
        22,
        "7-4 Late",
        0.098,
        0.34,
        0.5,
        0.69,
        0.707,
        0.088,
        0.33,
        0.45,
        0.731,
        0.01,
        0.02,
        0.05,
        0.333
      ],
      [
        1626195,
        "Hernangomez, Willy",
        6,
        58,
        20,
        "4-0 Very Late",
        0.084,
        0.16,
        0.43,
        0.36,
        0.46,
        0.051,
        0.07,
        0.26,
        0.267,
        0.034,
        0.09,
        0.17,
        0.5
      ]
    ]
  },
  {
    "name": "DribbleShooting",
    "headers": [
      "PLAYER_ID",
      "PLAYER_NAME_LAST_FIRST",
      "SORT_ORDER",
      "GP",
      "G",
      "DRIBBLE_RANGE",
      "FGA_FREQUENCY",
      "FGM",
      "FGA",
      "FG_PCT",
      "EFG_PCT",
      "FG2A_FREQUENCY",
      "FG2M",
      "FG2A",
      "FG2_PCT",
      "FG3A_FREQUENCY",
      "FG3M",
      "FG3A",
      "FG3_PCT"
    ],
    "rowSet": [
      [
        1626195,
        "Hernangomez, Willy",
        1,
        58,
        56,
        "0 Dribbles",
        0.747,
        1.97,
        3.81,
        0.516,
        0.548,
        0.618,
        1.72,
        3.16,
        0.546,
        0.128,
        0.24,
        0.66,
        0.368
      ],
      [
        1626195,
        "Hernangomez, Willy",
        2,
        58,
        30,
        "1 Dribble",
        0.152,
        0.38,
        0.78,
        0.489,
        0.489,
        0.152,
        0.38,
        0.78,
        0.489,
        0,
        0,
        0,
        null
      ],
      [
        1626195,
        "Hernangomez, Willy",
        3,
        58,
        11,
        "2 Dribbles",
        0.047,
        0.17,
        0.24,
        0.714,
        0.714,
        0.047,
        0.17,
        0.24,
        0.714,
        0,
        0,
        0,
        null
      ],
      [
        1626195,
        "Hernangomez, Willy",
        4,
        58,
        15,
        "3-6 Dribbles",
        0.054,
        0.12,
        0.28,
        0.438,
        0.469,
        0.051,
        0.1,
        0.26,
        0.4,
        0.003,
        0.02,
        0.02,
        1
      ]
    ]
  },
  {
    "name": "ClosestDefenderShooting",
    "headers": [
      "PLAYER_ID",
      "PLAYER_NAME_LAST_FIRST",
      "SORT_ORDER",
      "GP",
      "G",
      "CLOSE_DEF_DIST_RANGE",
      "FGA_FREQUENCY",
      "FGM",
      "FGA",
      "FG_PCT",
      "EFG_PCT",
      "FG2A_FREQUENCY",
      "FG2M",
      "FG2A",
      "FG2_PCT",
      "FG3A_FREQUENCY",
      "FG3M",
      "FG3A",
      "FG3_PCT"
    ],
    "rowSet": [
      [
        1626195,
        "Hernangomez, Willy",
        1,
        58,
        38,
        "0-2 Feet - Very Tight",
        0.25,
        0.55,
        1.28,
        0.432,
        0.432,
        0.25,
        0.55,
        1.28,
        0.432,
        0,
        0,
        0,
        null
      ],
      [
        1626195,
        "Hernangomez, Willy",
        2,
        58,
        50,
        "2-4 Feet - Tight",
        0.466,
        1.33,
        2.38,
        0.558,
        0.558,
        0.466,
        1.33,
        2.38,
        0.558,
        0,
        0,
        0,
        null
      ],
      [
        1626195,
        "Hernangomez, Willy",
        3,
        58,
        24,
        "4-6 Feet - Open",
        0.115,
        0.4,
        0.59,
        0.676,
        0.676,
        0.115,
        0.4,
        0.59,
        0.676,
        0,
        0,
        0,
        null
      ],
      [
        1626195,
        "Hernangomez, Willy",
        4,
        58,
        35,
        "6+ Feet - Wide Open",
        0.169,
        0.36,
        0.86,
        0.42,
        0.57,
        0.037,
        0.1,
        0.19,
        0.545,
        0.132,
        0.26,
        0.67,
        0.385
      ]
    ]
  },
  {
    "name": "ClosestDefender10ftPlusShooting",
    "headers": [
      "PLAYER_ID",
      "PLAYER_NAME_LAST_FIRST",
      "SORT_ORDER",
      "GP",
      "G",
      "CLOSE_DEF_DIST_RANGE",
      "FGA_FREQUENCY",
      "FGM",
      "FGA",
      "FG_PCT",
      "EFG_PCT",
      "FG2A_FREQUENCY",
      "FG2M",
      "FG2A",
      "FG2_PCT",
      "FG3A_FREQUENCY",
      "FG3M",
      "FG3A",
      "FG3_PCT"
    ],
    "rowSet": [
      [
        1626195,
        "Hernangomez, Willy",
        1,
        58,
        2,
        "0-2 Feet - Very Tight",
        0.007,
        0,
        0.03,
        0,
        0,
        0.007,
        0,
        0.03,
        0,
        0,
        0,
        0,
        null
      ],
      [
        1626195,
        "Hernangomez, Willy",
        2,
        58,
        2,
        "2-4 Feet - Tight",
        0.007,
        0.02,
        0.03,
        0.5,
        0.5,
        0.007,
        0.02,
        0.03,
        0.5,
        0,
        0,
        0,
        null
      ],
      [
        1626195,
        "Hernangomez, Willy",
        3,
        58,
        7,
        "4-6 Feet - Open",
        0.024,
        0.03,
        0.12,
        0.286,
        0.286,
        0.024,
        0.03,
        0.12,
        0.286,
        0,
        0,
        0,
        null
      ],
      [
        1626195,
        "Hernangomez, Willy",
        4,
        58,
        34,
        "6+ Feet - Wide Open",
        0.159,
        0.31,
        0.81,
        0.383,
        0.543,
        0.027,
        0.05,
        0.14,
        0.375,
        0.132,
        0.26,
        0.67,
        0.385
      ]
    ]
  },
  {
    "name": "TouchTimeShooting",
    "headers": [
      "PLAYER_ID",
      "PLAYER_NAME_LAST_FIRST",
      "SORT_ORDER",
      "GP",
      "G",
      "TOUCH_TIME_RANGE",
      "FGA_FREQUENCY",
      "FGM",
      "FGA",
      "FG_PCT",
      "EFG_PCT",
      "FG2A_FREQUENCY",
      "FG2M",
      "FG2A",
      "FG2_PCT",
      "FG3A_FREQUENCY",
      "FG3M",
      "FG3A",
      "FG3_PCT"
    ],
    "rowSet": [
      [
        1626195,
        "Hernangomez, Willy",
        1,
        58,
        56,
        "Touch < 2 Seconds",
        0.807,
        2.14,
        4.12,
        0.519,
        0.548,
        0.682,
        1.9,
        3.48,
        0.545,
        0.125,
        0.24,
        0.64,
        0.378
      ],
      [
        1626195,
        "Hernangomez, Willy",
        2,
        58,
        33,
        "Touch 2-6 Seconds",
        0.193,
        0.5,
        0.98,
        0.509,
        0.518,
        0.186,
        0.48,
        0.95,
        0.509,
        0.007,
        0.02,
        0.03,
        0.5
      ]
    ]
  }
]