[
  {
    "name": "Overall",
    "headers": [
      "PLAYER_ID",
      "PLAYER_NAME_LAST_FIRST",
      "SORT_ORDER",
      "GP",
      "G",
      "SHOT_TYPE",
      "FGA_FREQUENCY",
      "FGM",
      "FGA",
      "FG_PCT",
      "EFG_PCT",
      "FG2A_FREQUENCY",
      "FG2M",
      "FG2A",
      "FG2_PCT",
      "FG3A_FREQUENCY",
      "FG3M",
      "FG3A",
      "FG3_PCT"
    ],
    "rowSet": [
      [
        1629660,
        "Jerome, Ty",
        1,
        31,
        27,
        "Overall",
        1,
        1.23,
        3.61,
        0.339,
        0.402,
        0.554,
        0.77,
        2,
        0.387,
        0.446,
        0.45,
        1.61,
        0.28
      ]
    ]
  },
  {
    "name": "GeneralShooting",
    "headers": [
      "PLAYER_ID",
      "PLAYER_NAME_LAST_FIRST",
      "SORT_ORDER",
      "GP",
      "G",
      "SHOT_TYPE",
      "FGA_FREQUENCY",
      "FGM",
      "FGA",
      "FG_PCT",
      "EFG_PCT",
      "FG2A_FREQUENCY",
      "FG2M",
      "FG2A",
      "FG2_PCT",
      "FG3A_FREQUENCY",
      "FG3M",
      "FG3A",
      "FG3_PCT"
    ],
    "rowSet": [
      [
        1629660,
        "Jerome, Ty",
        1,
        31,
        23,
        "Catch and Shoot",
        0.375,
        0.35,
        1.35,
        0.262,
        0.369,
        0.027,
        0.06,
        0.1,
        0.667,
        0.348,
        0.29,
        1.26,
        0.231
      ],
      [
        1629660,
        "Jerome, Ty",
        2,
        31,
        18,
        "Pull Ups",
        0.313,
        0.45,
        1.13,
        0.4,
        0.471,
        0.214,
        0.29,
        0.77,
        0.375,
        0.098,
        0.16,
        0.35,
        0.455
      ],
      [
        1629660,
        "Jerome, Ty",
        3,
        31,
        20,
        "Less than 10 ft",
        0.313,
        0.42,
        1.13,
        0.371,
        0.371,
        0.313,
        0.42,
        1.13,
        0.371,
        0,
        0,
        0,
        null
      ]
    ]
  },
  {
    "name": "ShotClockShooting",
    "headers": [
      "PLAYER_ID",
      "PLAYER_NAME_LAST_FIRST",
      "SORT_ORDER",
      "GP",
      "G",
      "SHOT_CLOCK_RANGE",
      "FGA_FREQUENCY",
      "FGM",
      "FGA",
      "FG_PCT",
      "EFG_PCT",
      "FG2A_FREQUENCY",
      "FG2M",
      "FG2A",
      "FG2_PCT",
      "FG3A_FREQUENCY",
      "FG3M",
      "FG3A",
      "FG3_PCT"
    ],
    "rowSet": [
      [
        1629660,
        "Jerome, Ty",
        1,
        31,
        1,
        "24-22",
        0.009,
        0,
        0.03,
        0,
        0,
        0,
        0,
        0,
        null,
        0.009,
        0,
        0.03,
        0
      ],
      [
        1629660,
        "Jerome, Ty",
        2,
        31,
        9,
        "22-18 Very Early",
        0.107,
        0.06,
        0.39,
        0.167,
        0.25,
        0.045,
        0,
        0.16,
        0,
        0.063,
        0.06,
        0.23,
        0.286
      ],
      [
        1629660,
        "Jerome, Ty",
        3,
        31,
        14,
        "18-15 Early",
        0.179,
        0.19,
        0.65,
        0.3,
        0.325,
        0.089,
        0.16,
        0.32,
        0.5,
        0.089,
        0.03,
        0.32,
        0.1
      ],
      [
        1629660,
        "Jerome, Ty",
        4,
        31,
        21,
        "15-7 Average",
        0.482,
        0.68,
        1.74,
        0.389,
        0.472,
        0.286,
        0.39,
        1.03,
        0.375,
        0.196,
        0.29,
        0.71,
        0.409
      ],
      [
        1629660,
        "Jerome, Ty",
        5,
        31,
        9,
        "7-4 Late",
        0.116,
        0.19,
        0.42,
        0.462,
        0.538,
        0.063,
        0.13,
        0.23,
        0.571,
        0.054,
        0.06,
        0.19,
        0.333
      ],
      [
        1629660,
        "Jerome, Ty",
        6,
        31,
        9,
        "4-0 Very Late",
        0.107,
        0.1,
        0.39,
        0.25,
        0.25,
        0.071,
        0.1,
        0.26,
        0.375,
        0.036,
        0,
        0.13,
        0
      ]
    ]
  },
  {
    "name": "DribbleShooting",
    "headers": [
      "PLAYER_ID",
      "PLAYER_NAME_LAST_FIRST",
      "SORT_ORDER",
      "GP",
      "G",
      "DRIBBLE_RANGE",
      "FGA_FREQUENCY",
      "FGM",
      "FGA",
      "FG_PCT",
      "EFG_PCT",
      "FG2A_FREQUENCY",
      "FG2M",
      "FG2A",
      "FG2_PCT",
      "FG3A_FREQUENCY",
      "FG3M",
      "FG3A",
      "FG3_PCT"
    ],
    "rowSet": [
      [
        1629660,
        "Jerome, Ty",
        1,
        31,
        23,
        "0 Dribbles",
        0.402,
        0.42,
        1.45,
        0.289,
        0.389,
        0.054,
        0.13,
        0.19,
        0.667,
        0.348,
        0.29,
        1.26,
        0.231
      ],
      [
        1629660,
        "Jerome, Ty",
        2,
        31,
        11,
        "1 Dribble",
        0.116,
        0.13,
        0.42,
        0.308,
        0.423,
        0.063,
        0.03,
        0.23,
        0.143,
        0.054,
        0.1,
        0.19,
        0.5
      ],
      [
        1629660,
        "Jerome, Ty",
        3,
        31,
        7,
        "2 Dribbles",
        0.089,
        0.06,
        0.32,
        0.2,
        0.2,
        0.071,
        0.06,
        0.26,
        0.25,
        0.018,
        0,
        0.06,
        0
      ],
      [
        1629660,
        "Jerome, Ty",
        4,
        31,
        11,
        "3-6 Dribbles",
        0.134,
        0.19,
        0.48,
        0.4,
        0.467,
        0.107,
        0.13,
        0.39,
        0.333,
        0.027,
        0.06,
        0.1,
        0.667
      ],
      [
        1629660,
        "Jerome, Ty",
        5,
        31,
        17,
        "7+ Dribbles",
        0.259,
        0.42,
        0.94,
        0.448,
        0.448,
        0.259,
        0.42,
        0.94,
        0.448,
        0,
        0,
        0,
        null
      ]
    ]
  },
  {
    "name": "ClosestDefenderShooting",
    "headers": [
      "PLAYER_ID",
      "PLAYER_NAME_LAST_FIRST",
      "SORT_ORDER",
      "GP",
      "G",
      "CLOSE_DEF_DIST_RANGE",
      "FGA_FREQUENCY",
      "FGM",
      "FGA",
      "FG_PCT",
      "EFG_PCT",
      "FG2A_FREQUENCY",
      "FG2M",
      "FG2A",
      "FG2_PCT",
      "FG3A_FREQUENCY",
      "FG3M",
      "FG3A",
      "FG3_PCT"
    ],
    "rowSet": [
      [
        1629660,
        "Jerome, Ty",
        1,
        31,
        5,
        "0-2 Feet - Very Tight",
        0.054,
        0.1,
        0.19,
        0.5,
        0.5,
        0.054,
        0.1,
        0.19,
        0.5,
        0,
        0,
        0,
        null
      ],
      [
        1629660,
        "Jerome, Ty",
        2,
        31,
        20,
        "2-4 Feet - Tight",
        0.42,
        0.42,
        1.52,
        0.277,
        0.277,
        0.384,
        0.42,
        1.39,
        0.302,
        0.036,
        0,
        0.13,
        0
      ],
      [
        1629660,
        "Jerome, Ty",
        3,
        31,
        17,
        "4-6 Feet - Open",
        0.205,
        0.29,
        0.74,
        0.391,
        0.478,
        0.063,
        0.16,
        0.23,
        0.714,
        0.143,
        0.13,
        0.52,
        0.25
      ],
      [
        1629660,
        "Jerome, Ty",
        4,
        31,
        18,
        "6+ Feet - Wide Open",
        0.321,
        0.42,
        1.16,
        0.361,
        0.5,
        0.054,
        0.1,
        0.19,
        0.5,
        0.268,
        0.32,
        0.97,
        0.333
      ]
    ]
  },
  {
    "name": "ClosestDefender10ftPlusShooting",
    "headers": [
      "PLAYER_ID",
      "PLAYER_NAME_LAST_FIRST",
      "SORT_ORDER",
      "GP",
      "G",
      "CLOSE_DEF_DIST_RANGE",
      "FGA_FREQUENCY",
      "FGM",
      "FGA",
      "FG_PCT",
      "EFG_PCT",
      "FG2A_FREQUENCY",
      "FG2M",
      "FG2A",
      "FG2_PCT",
      "FG3A_FREQUENCY",
      "FG3M",
      "FG3A",
      "FG3_PCT"
    ],
    "rowSet": [
      [
        1629660,
        "Jerome, Ty",
        1,
        31,
        2,
        "0-2 Feet - Very Tight",
        0.018,
        0,
        0.06,
        0,
        0,
        0.018,
        0,
        0.06,
        0,
        0,
        0,
        0,
        null
      ],
      [
        1629660,
        "Jerome, Ty",
        2,
        31,
        11,
        "2-4 Feet - Tight",
        0.161,
        0.16,
        0.58,
        0.278,
        0.278,
        0.125,
        0.16,
        0.45,
        0.357,
        0.036,
        0,
        0.13,
        0
      ],
      [
        1629660,
        "Jerome, Ty",
        3,
        31,
        16,
        "4-6 Feet - Open",
        0.188,
        0.23,
        0.68,
        0.333,
        0.429,
        0.045,
        0.1,
        0.16,
        0.6,
        0.143,
        0.13,
        0.52,
        0.25
      ],
      [
        1629660,
        "Jerome, Ty",
        4,
        31,
        18,
        "6+ Feet - Wide Open",
        0.321,
        0.42,
        1.16,
        0.361,
        0.5,
        0.054,
        0.1,
        0.19,
        0.5,
        0.268,
        0.32,
        0.97,
        0.333
      ]
    ]
  },
  {
    "name": "TouchTimeShooting",
    "headers": [
      "PLAYER_ID",
      "PLAYER_NAME_LAST_FIRST",
      "SORT_ORDER",
      "GP",
      "G",
      "TOUCH_TIME_RANGE",
      "FGA_FREQUENCY",
      "FGM",
      "FGA",
      "FG_PCT",
      "EFG_PCT",
      "FG2A_FREQUENCY",
      "FG2M",
      "FG2A",
      "FG2_PCT",
      "FG3A_FREQUENCY",
      "FG3M",
      "FG3A",
      "FG3_PCT"
    ],
    "rowSet": [
      [
        1629660,
        "Jerome, Ty",
        1,
        31,
        24,
        "Touch < 2 Seconds",
        0.455,
        0.52,
        1.65,
        0.314,
        0.422,
        0.071,
        0.16,
        0.26,
        0.625,
        0.384,
        0.35,
        1.39,
        0.256
      ],
      [
        1629660,
        "Jerome, Ty",
        2,
        31,
        17,
        "Touch 2-6 Seconds",
        0.277,
        0.29,
        1,
        0.29,
        0.339,
        0.214,
        0.19,
        0.77,
        0.25,
        0.063,
        0.1,
        0.23,
        0.429
      ],
      [
        1629660,
        "Jerome, Ty",
        3,
        31,
        17,
        "Touch 6+ Seconds",
        0.268,
        0.42,
        0.97,
        0.433,
        0.433,
        0.268,
        0.42,
        0.97,
        0.433,
        0,
        0,
        0,
        null
      ]
    ]
  }
]